collagen/__init__.py
collagen/_version.py
collagen/cli.py
collagen/vm.py
collagen/standard/__init__.py
collagen/standard/branching.py
collagen/standard/loops.py
collagen/standard/operators.py
collagen/standard/other.py
collagen/standard/stack_operations.py
collagen/standard/types.py
collagen/standard/resources/__init__.py
collagen/standard/resources/file.py
collagen/standard/resources/hson.py
collagen/standard/resources/json.py
collagen/standard/resources/json5.py
collagen/standard/resources/methods.py
collagen/standard/resources/variable.py
mkdocstrings_handlers/collagen/__init__.py
mkdocstrings_handlers/collagen/handler.py
mkdocstrings_handlers/collagen/templates/terminal/metadata.html
mkdocstrings_handlers/collagen/templates/terminal/ops.html
collagen-0.2.0.dist-info/LICENSE
collagen-0.2.0.dist-info/METADATA
collagen-0.2.0.dist-info/WHEEL
collagen-0.2.0.dist-info/entry_points.txt
collagen-0.2.0.dist-info/top_level.txt
collagen-0.2.0.dist-info/RECORD
