Metadata-Version: 2.1
Name: collagen
Version: 0.2.0
Summary: A virtual stack machine that executes Python code based on instructions provided in a JSON file.
Home-page: https://github.com/LiamBindle/collagen.git
License-File: LICENSE
Provides-Extra: dev
Requires-Dist: flake8 ; extra == 'dev'
Requires-Dist: pytest ; extra == 'dev'
Provides-Extra: docs
Requires-Dist: mkdocs ; extra == 'docs'
Requires-Dist: mkdocstrings[python] ; extra == 'docs'
Requires-Dist: mkdocs-terminal ; extra == 'docs'
Requires-Dist: pytkdocs[numpy-style] (>=0.5.0) ; extra == 'docs'
Provides-Extra: hjson
Requires-Dist: hjson ; extra == 'hjson'
Provides-Extra: json5
Requires-Dist: json5 ; extra == 'json5'
